spectquant/__init__.py
spectquant/create_segs.py
spectquant/morphology.py
spectquant/septum.py
spectquant/suv.py
spectquant/tbr.py
spectquant/uptake.py
spectquant/utils.py
spectquant/volume.py
spectquant-0.1.20.dist-info/licenses/LICENSE
spectquant-0.1.20.dist-info/METADATA
spectquant-0.1.20.dist-info/WHEEL
spectquant-0.1.20.dist-info/top_level.txt
spectquant-0.1.20.dist-info/RECORD
