Metadata-Version: 2.4
Name: spectquant
Version: 0.1.20
Summary: Specialized Package for Extracting Image Features for Cardiac Amyloidosis Quantification on SPECT.
Home-page: https://github.com/MarkusStefan/spectquant
Author: MarkusStefan
Author-email: markus.koefler11@gmail.com
License: MIT License
Classifier: Development Status :: 3 - Alpha
Classifier: Intended Audience :: Developers
Classifier: Intended Audience :: Science/Research
Classifier: License :: OSI Approved :: MIT License
Classifier: Operating System :: OS Independent
Classifier: Topic :: Scientific/Engineering
Classifier: Topic :: Scientific/Engineering :: Medical Science Apps.
Classifier: Topic :: Scientific/Engineering :: Image Processing
Classifier: Topic :: Scientific/Engineering :: Visualization
Classifier: Programming Language :: Python :: 3.7
Classifier: Programming Language :: Python :: 3.8
Classifier: Programming Language :: Python :: 3.9
Classifier: Programming Language :: Python :: 3.10
Classifier: Programming Language :: Python :: 3.11
Classifier: Programming Language :: Python :: 3.12
License-File: LICENSE
Requires-Dist: matplotlib
Requires-Dist: nibabel
Requires-Dist: nilearn
Requires-Dist: numpy==1.23.5; python_version < "3.12"
Requires-Dist: numpy>=1.26.4; python_version >= "3.12"
Requires-Dist: pandas==2.2.2
Requires-Dist: scipy==1.13.0
Requires-Dist: plotly
Requires-Dist: seaborn
Requires-Dist: TotalSegmentator
Requires-Dist: pygments
Requires-Dist: jupyter-client
Provides-Extra: gpu
Dynamic: author
Dynamic: author-email
Dynamic: classifier
Dynamic: description
Dynamic: description-content-type
Dynamic: home-page
Dynamic: license
Dynamic: license-file
Dynamic: provides-extra
Dynamic: requires-dist
Dynamic: summary
